funcclasses/__about__.py
funcclasses/__init__.py
funcclasses/partial.py
funcclasses/types.py
funcclasses-0.0.2.dist-info/METADATA
funcclasses-0.0.2.dist-info/WHEEL
funcclasses-0.0.2.dist-info/licenses/LICENSE.txt
funcclasses-0.0.2.dist-info/RECORD
