Metadata-Version: 2.1
Name: funcclasses
Version: 0.0.2
Project-URL: Documentation, https://github.com/joshua-auchincloss/funcclasses#readme
Project-URL: Issues, https://github.com/joshua-auchincloss/funcclasses/issues
Project-URL: Source, https://github.com/joshua-auchincloss/funcclasses
Author-email: joshua-auchincloss <joshua.auchincloss@proton.me>
License-Expression: MIT
License-File: LICENSE.txt
Classifier: Development Status :: 4 - Beta
Classifier: Programming Language :: Python
Classifier: Programming Language :: Python :: 3.10
Classifier: Programming Language :: Python :: 3.11
Classifier: Programming Language :: Python :: Implementation :: CPython
Classifier: Programming Language :: Python :: Implementation :: PyPy
Requires-Python: >=3.10
